lpips/__init__.py
lpips/lpips.py
lpips/pretrained_networks.py
lpips/trainer.py
lpips/weights/v0.0/alex.pth
lpips/weights/v0.0/squeeze.pth
lpips/weights/v0.0/vgg.pth
lpips/weights/v0.1/alex.pth
lpips/weights/v0.1/squeeze.pth
lpips/weights/v0.1/vgg.pth
lpips-0.1.4.dist-info/LICENSE
lpips-0.1.4.dist-info/METADATA
lpips-0.1.4.dist-info/WHEEL
lpips-0.1.4.dist-info/top_level.txt
lpips-0.1.4.dist-info/RECORD
