Metadata-Version: 2.1
Name: lpips
Version: 0.1.4
Summary: LPIPS Similarity metric
Home-page: https://github.com/richzhang/PerceptualSimilarity
Author: Richard Zhang
Author-email: rizhang@adobe.com
License: UNKNOWN
Platform: UNKNOWN
Classifier: Programming Language :: Python :: 3
Classifier: License :: OSI Approved :: BSD License
Classifier: Operating System :: OS Independent
